notify_discord/__init__.py
notify_discord/command_line.py
notify_discord-0.1.dist-info/LICENCE.md
notify_discord-0.1.dist-info/METADATA
notify_discord-0.1.dist-info/WHEEL
notify_discord-0.1.dist-info/entry_points.txt
notify_discord-0.1.dist-info/top_level.txt
notify_discord-0.1.dist-info/RECORD
