Metadata-Version: 2.1
Name: notify-discord
Version: 0.1
Summary: A simple python script to push notification on discord's channel using webhooks
Home-page: UNKNOWN
Author: Jean-Luc Szpyrka
Author-email: jeanluc.szpyrka@gmail.com
License: UNKNOWN
Keywords: discord,webhook,notify
Platform: UNKNOWN
Classifier: Programming Language :: Python :: 3
Classifier: License :: OSI Approved :: MIT License
Classifier: Operating System :: OS Independent
Requires-Dist: requests
